{
	"home": "index.html",
	"sobreMim": "sobre-mim.html",
	"avaliacaoNeuropsicologica": "avaliacao-neuropsicologica.html",
	"psicoterapia": "psicoterapia.html",
	"testeRapido": "teste-rapido.html",
	"contato": "contato.html",

	"email": "mailto:psicosabinastedile@gmail.com",
	"instagram": "https://www.instagram.com/psicosabinastedile",
	"lattes": "http://lattes.cnpq.br/9146600080670922",
	"linkedin": "https://www.linkedin.com/in/sabina-stedile-73b738167/",
	"whatsapp": "https://wa.me/5551998990016",
	"youtube": "https://youtube.com/@psicosabinastedile?si=SDraORFM41unz0n2"
}
